libplasma/__init__.py
libplasma/plasma.py
libplasma/src/__init__.py
libplasma/src/component.py
libplasma/src/dataset.py
libplasma/src/executor.py
libplasma/src/utils.py
libplasma/src/workflow.py
libplasma-0.1.2.dist-info/METADATA
libplasma-0.1.2.dist-info/WHEEL
libplasma-0.1.2.dist-info/top_level.txt
libplasma-0.1.2.dist-info/RECORD
